{"data_mtime": 1608994153, "dep_lines": [1, 2, 3, 4, 5, 22, 23, 24, 1, 1, 1], "dep_prios": [5, 5, 5, 5, 5, 5, 5, 5, 5, 30, 30], "dependencies": ["httpcore._async.base", "httpcore._async.connection_pool", "httpcore._async.http_proxy", "httpcore._bytestreams", "httpcore._exceptions", "httpcore._sync.base", "httpcore._sync.connection_pool", "httpcore._sync.http_proxy", "builtins", "abc", "typing"], "hash": "c509993d581365a50eace25a20f4f59ca3e6835b6e8b742c9b27603f7c5d8f35", "id": "httpcore", "ignore_all": true, "interface_hash": "3b1396832e2c787139c1668b32b815e824d6a1dab71afc75a8dd9d1608b9d8c9", "mtime": 1606888785, "options": {"allow_redefinition": false, "allow_untyped_globals": false, "always_false": [], "always_true": [], "bazel": false, "check_untyped_defs": false, "disallow_any_decorated": false, "disallow_any_explicit": false, "disallow_any_expr": false, "disallow_any_generics": false, "disallow_any_unimported": false, "disallow_incomplete_defs": false, "disallow_subclassing_any": false, "disallow_untyped_calls": false, "disallow_untyped_decorators": false, "disallow_untyped_defs": false, "follow_imports": "normal", "follow_imports_for_stubs": false, "ignore_errors": false, "ignore_missing_imports": false, "implicit_reexport": true, "local_partial_types": false, "mypyc": false, "no_implicit_optional": false, "platform": "linux", "plugins": [], "show_none_errors": true, "strict_equality": false, "strict_optional": true, "strict_optional_whitelist": null, "warn_no_return": true, "warn_return_any": false, "warn_unreachable": false, "warn_unused_ignores": false}, "path": "/home/jacklanda/.local/lib/python3.8/site-packages/httpcore/__init__.py", "plugin_data": null, "size": 1493, "suppressed": [], "version_id": "0.770"}